[{"name":"A0","kind":"author","given":80.0,"author_id":"A0","reviews_given":0.0,"outline":"none","first_story":null,"y":-0.0206038468,"x":0.0558758062,"day":0,"incoming":114,"fill":"author"},{"name":"R6","kind":"reviewer","given":120,"author_id":"R6","reviews_given":4,"outline":null,"first_story":null,"y":0.35711432,"x":-0.8386964214,"day":12,"incoming":0.0,"fill":"reviewer"},{"name":"R5","kind":"reviewer","given":390,"author_id":"R5","reviews_given":31,"outline":null,"first_story":null,"y":-0.847223332,"x":0.5565321614,"day":0,"incoming":0.0,"fill":"reviewer"},{"name":"R9","kind":"reviewer","given":120,"author_id":"R9","reviews_given":4,"outline":null,"first_story":null,"y":0.9492038126,"x":0.1427429941,"day":24,"incoming":0.0,"fill":"reviewer"},{"name":"R8","kind":"reviewer","given":150,"author_id":"R8","reviews_given":7,"outline":null,"first_story":null,"y":0.7173677302,"x":0.7019576508,"day":1,"incoming":0.0,"fill":"reviewer"},{"name":"R2","kind":"reviewer","given":590,"author_id":"R2","reviews_given":51,"outline":null,"first_story":null,"y":0.8183893613,"x":-0.448935563,"day":2,"incoming":0.0,"fill":"reviewer"},{"name":"R4","kind":"reviewer","given":120,"author_id":"R4","reviews_given":4,"outline":null,"first_story":null,"y":0.1963928999,"x":1.0,"day":14,"incoming":0.0,"fill":"reviewer"},{"name":"R3","kind":"reviewer","given":180,"author_id":"R3","reviews_given":10,"outline":null,"first_story":null,"y":-1.0,"x":-0.0226585241,"day":2,"incoming":0.0,"fill":"reviewer"},{"name":"R1","kind":"reviewer","given":90,"author_id":"R1","reviews_given":1,"outline":null,"first_story":null,"y":-0.2442212202,"x":-0.8972661378,"day":13,"incoming":0.0,"fill":"reviewer"},{"name":"R0","kind":"reviewer","given":90,"author_id":"R0","reviews_given":1,"outline":null,"first_story":null,"y":-0.7587808915,"x":-0.5788025798,"day":10,"incoming":0.0,"fill":"reviewer"},{"name":"R7","kind":"reviewer","given":90,"author_id":"R7","reviews_given":1,"outline":null,"first_story":null,"y":-0.4052508418,"x":0.9638148508,"day":9,"incoming":0.0,"fill":"reviewer"}]